LICENSE
MANIFEST.in
README.md
setup.py
setup_common.py
dffml_config_png/__init__.py
dffml_config_png/configloader.py
dffml_config_png/version.py
dffml_config_png.egg-info/PKG-INFO
dffml_config_png.egg-info/SOURCES.txt
dffml_config_png.egg-info/dependency_links.txt
dffml_config_png.egg-info/entry_points.txt
dffml_config_png.egg-info/requires.txt
dffml_config_png.egg-info/top_level.txt
tests/__init__.py
tests/test_config.py